ogscm/__init__.py
ogscm/app/__init__.py
ogscm/app/builder.py
ogscm/app/deployer.py
ogscm/building_blocks/__init__.py
ogscm/building_blocks/ccache.py
ogscm/building_blocks/lmod.py
ogscm/building_blocks/ogs.py
ogscm/building_blocks/ogs_base.py
ogscm/building_blocks/osu_benchmarks.py
ogscm/building_blocks/paraview.py
ogscm/building_blocks/pm_easybuild.py
ogscm/cli.py
ogscm/common.py
ogscm/config.py
ogscm/recipes/__init__.py
ogscm/recipes/_template.py
ogscm/recipes/compiler.py
ogscm/recipes/files/jupyterlab-gitlab_settings.json
ogscm/recipes/mpi-entrypoint.sh
ogscm/recipes/mpi.py
ogscm/recipes/ogs.py
ogscm/recipes/ogs_jupyter.py
ogscm/recipes/ogs_vscode.py
ogscm/recipes/ogs_web.py
ogscm/recipes/python_vtk.py
ogscm/version.py
ogscm-2.5.0.dist-info/LICENSE
ogscm-2.5.0.dist-info/METADATA
ogscm-2.5.0.dist-info/WHEEL
ogscm-2.5.0.dist-info/entry_points.txt
ogscm-2.5.0.dist-info/RECORD
