Metadata-Version: 2.1
Name: ogscm
Version: 2.5.0
Summary: OGS Container Maker
Home-page: https://gitlab.opengeosys.org/ogs/container-maker
License: BSD 3-clause
Author: Lars Bilke
Author-email: lars.bilke@ufz.de
Requires-Python: >=3.8,<4.0
Classifier: License :: Other/Proprietary License
Classifier: Programming Language :: Python :: 3
Classifier: Programming Language :: Python :: 3.8
Classifier: Programming Language :: Python :: 3.9
Classifier: Programming Language :: Python :: 3.10
Classifier: Programming Language :: Python :: 3.11
Classifier: Programming Language :: Python :: 3.12
Requires-Dist: PyYAML (>=6.0,<7.0)
Requires-Dist: archspec (>=0.2.4,<0.3.0)
Requires-Dist: hpccm (>=24.8.0,<25.0.0)
Requires-Dist: packaging (>=24.1,<25.0)
Requires-Dist: requests (>=2.24.0,<3.0.0)
Requires-Dist: setuptools (>=72.1.0,<73.0.0)
Project-URL: OpenGepSys project, https://www.opengeosys.org
Project-URL: Repository, https://gitlab.opengeosys.org/ogs/container-maker
